Metadata-Version: 2.1
Name: pylammps
Version: 0.0.1
Summary: pylammps
Home-page: https://gitee.com/alkemie_gjwang/pylammps
Author: Guanjie Wang
Author-email: gjwang@buaa.edu.cn
License: MIT
Platform: UNKNOWN
